Popitto/Framework.py
Popitto/__init__.py
Popitto-0.1.2.dist-info/METADATA
Popitto-0.1.2.dist-info/WHEEL
Popitto-0.1.2.dist-info/top_level.txt
Popitto-0.1.2.dist-info/RECORD
