Metadata-Version: 2.1
Name: Popitto
Version: 0.1.2
Summary: Basic Pop-It package
Author: Dragjon
Author-email: <magiciandragjon@gmail.com>
Keywords: python,game,board,boardgame
Classifier: Development Status :: 1 - Planning
Classifier: Intended Audience :: Developers
Classifier: Programming Language :: Python :: 3
Classifier: License :: OSI Approved :: MIT License
Classifier: Operating System :: OS Independent
